vm_translator/__init__.py
vm_translator/__main__.py
vm_translator-0.1.dist-info/DESCRIPTION.rst
vm_translator-0.1.dist-info/METADATA
vm_translator-0.1.dist-info/RECORD
vm_translator-0.1.dist-info/WHEEL
vm_translator-0.1.dist-info/entry_points.txt
vm_translator-0.1.dist-info/metadata.json
vm_translator-0.1.dist-info/top_level.txt
