Metadata-Version: 2.0
Name: vm-translator
Version: 0.1
Summary: Translates VM files into Hack assembly files.
Home-page: https://github.com/marcusmonteiro/coursera-nand2tetris/tree/master/projects/07/vm_translator
Author: Marcus Vinicius Monteiro de Souza
Author-email: mvsouza007@gmail.com
License: MIT
Keywords: vm translator hack assembly
Platform: UNKNOWN
Classifier: Development Status :: 4 - Beta
Classifier: Environment :: Console
Classifier: Intended Audience :: Developers
Classifier: License :: OSI Approved :: MIT License
Classifier: Operating System :: MacOS :: MacOS X
Classifier: Operating System :: Microsoft :: Windows
Classifier: Operating System :: POSIX
Classifier: Topic :: Software Development :: Assemblers
Classifier: Topic :: Software Development :: Code Generators
Classifier: Topic :: Software Development :: Compilers
Classifier: Programming Language :: Python :: 3.6
Classifier: Programming Language :: Python :: 3.7
Requires-Python: >=3.6
